odoo/addons/sale_blanket_order_discount/LICENSE
odoo/addons/sale_blanket_order_discount/README.rst
odoo/addons/sale_blanket_order_discount/__init__.py
odoo/addons/sale_blanket_order_discount/__manifest__.py
odoo/addons/sale_blanket_order_discount/images/screen.png
odoo/addons/sale_blanket_order_discount/models/__init__.py
odoo/addons/sale_blanket_order_discount/models/blanket_order.py
odoo/addons/sale_blanket_order_discount/static/description/icon.png
odoo/addons/sale_blanket_order_discount/static/description/index.html
odoo/addons/sale_blanket_order_discount/tests/TEST_INSTRUCTIONS.rst
odoo/addons/sale_blanket_order_discount/views/view_blanket_order_form.xml
odoo/addons/sale_blanket_order_discount/views/view_create_sale_order.xml
odoo/addons/sale_blanket_order_discount/wizard/__init__.py
odoo/addons/sale_blanket_order_discount/wizard/create_sale_orders.py
odoo_addon_sale_blanket_order_discount-16.0.1.0.0.dist-info/METADATA
odoo_addon_sale_blanket_order_discount-16.0.1.0.0.dist-info/WHEEL
odoo_addon_sale_blanket_order_discount-16.0.1.0.0.dist-info/top_level.txt
odoo_addon_sale_blanket_order_discount-16.0.1.0.0.dist-info/RECORD
